cminx/__init__.py
cminx/aggregator.py
cminx/config.py
cminx/config_default.yaml
cminx/documentation_types.py
cminx/documenter.py
cminx/exceptions.py
cminx/rstwriter.py
cminx/parser/CMake.g4
cminx/parser/CMake.interp
cminx/parser/CMake.tokens
cminx/parser/CMakeLexer.interp
cminx/parser/CMakeLexer.py
cminx/parser/CMakeLexer.tokens
cminx/parser/CMakeListener.py
cminx/parser/CMakeParser.py
cminx/parser/CMakeVisitor.py
cminx/parser/__init__.py
cminx-1.1.13.dist-info/licenses/LICENSE
cminx-1.1.13.dist-info/METADATA
cminx-1.1.13.dist-info/WHEEL
cminx-1.1.13.dist-info/entry_points.txt
cminx-1.1.13.dist-info/top_level.txt
cminx-1.1.13.dist-info/RECORD
