Metadata-Version: 2.4
Name: CMinx
Version: 1.1.13
Summary: Documentation Generator for the CMake Language
Author: CMakePP
License:                                  Apache License
Project-URL: GitHub, https://github.com/CMakePP/CMinx
Keywords: CMake,Documentation
Classifier: Development Status :: 5 - Production/Stable
Classifier: License :: OSI Approved :: Apache Software License
Classifier: Programming Language :: Python :: 3 :: Only
Classifier: Topic :: Documentation
Classifier: Topic :: Software Development :: Documentation
Classifier: Topic :: Software Development :: Build Tools
License-File: LICENSE
Requires-Dist: antlr4-python3-runtime==4.13.2
Requires-Dist: confuse>=1.7
Requires-Dist: pathspec>=0.9.0
Provides-Extra: testing
Requires-Dist: coverage; extra == "testing"
Requires-Dist: docutils>=0.10; extra == "testing"
Requires-Dist: pytest; extra == "testing"
Requires-Dist: pytest-cov; extra == "testing"
Dynamic: license-file
